webexbotsdk/__init__.py
webexbotsdk/exception.py
webexbotsdk/tinydb.py
webexbotsdk/teams/__init__.py
webexbotsdk/teams/bot.py
webexbotsdk/teams/hook.py
webexbotsdk/teams/util.py
webexbotsdk-0.2.6.dist-info/LICENSE
webexbotsdk-0.2.6.dist-info/METADATA
webexbotsdk-0.2.6.dist-info/WHEEL
webexbotsdk-0.2.6.dist-info/top_level.txt
webexbotsdk-0.2.6.dist-info/RECORD
