Metadata-Version: 2.1
Name: webexbotsdk
Version: 0.2.6
Summary: Webex bot creation framework and tools
License: The MIT License (MIT)
Project-URL: Source, https://github.com/xharriscisco/WebexPythonBotSDK
Keywords: cisco,webex,teams,bot,python,framework,enterprise,messaging
Classifier: License :: OSI Approved :: MIT License
Classifier: Development Status :: 3 - Alpha
Classifier: Topic :: Communications :: Chat
Requires-Python: >=3
License-File: LICENSE
Requires-Dist: bottle
Requires-Dist: webexteamssdk
Requires-Dist: pyngrok
Requires-Dist: tinydb
Requires-Dist: tinydb-encrypted-jsonstorage
